yggdrasil/__init__.py
yggdrasil/authenticate.py
yggdrasil/invalidate.py
yggdrasil/refresh.py
yggdrasil/signout.py
yggdrasil/validate.py
yggdrasil_py-1.1.0.dist-info/LICENSE.txt
yggdrasil_py-1.1.0.dist-info/METADATA
yggdrasil_py-1.1.0.dist-info/WHEEL
yggdrasil_py-1.1.0.dist-info/top_level.txt
yggdrasil_py-1.1.0.dist-info/RECORD
